tts/TTS.py
tts/__init__.py
brnow-0.1.2.dist-info/LICENSE
brnow-0.1.2.dist-info/METADATA
brnow-0.1.2.dist-info/WHEEL
brnow-0.1.2.dist-info/top_level.txt
brnow-0.1.2.dist-info/RECORD
